plover_stenograph/__init__.py
plover_stenograph/usb.py
plover_stenograph/wifi.py
stenograph/__init__.py
stenograph/exception.py
stenograph/machine.py
stenograph/packet.py
stenograph/stroke.py
plover_stenograph-1.0.dist-info/METADATA
plover_stenograph-1.0.dist-info/WHEEL
plover_stenograph-1.0.dist-info/entry_points.txt
plover_stenograph-1.0.dist-info/top_level.txt
plover_stenograph-1.0.dist-info/zip-safe
plover_stenograph-1.0.dist-info/RECORD
