Metadata-Version: 2.1
Name: plover-stenograph
Version: 1.0
Summary: Plover plugin for Stenograph machines
Home-page: UNKNOWN
License: UNKNOWN
Keywords: plover plover_plugin
Platform: UNKNOWN
Classifier: Programming Language :: Python :: 3.9
Requires-Dist: plover (>=4.0.0.dev10)
Requires-Dist: more-itertools
Requires-Dist: pyusb (>=1.0.0) ; platform_system != "Windows"
